promptr/__init__.py
promptr/test/__init__.py
promptr/test/test_promptr.py
promptr-0.2.0.dist-info/LICENSE
promptr-0.2.0.dist-info/METADATA
promptr-0.2.0.dist-info/WHEEL
promptr-0.2.0.dist-info/top_level.txt
promptr-0.2.0.dist-info/RECORD
