Metadata-Version: 2.1
Name: promptr
Version: 0.2.0
Summary: promptr is a toolkit for building CLI shells, similar to that found on a Cisco router.
Home-page: https://github.com/mattdavis90/promptr
Author: Matt Davis
Author-email: mattdavis90@googlemail.com
License: MIT
Platform: UNKNOWN
Classifier: License :: OSI Approved :: MIT License
Classifier: Programming Language :: Python :: 3
Classifier: Programming Language :: Python :: 3.6
Classifier: Programming Language :: Python :: 3.7
Classifier: Programming Language :: Python :: Implementation :: CPython
Classifier: Programming Language :: Python :: Implementation :: PyPy
Requires-Dist: six
Requires-Dist: prompt-toolkit
